webwombat/__init__.py
webwombat/__main__.py
webwombat/buffers.py
webwombat/certs.py
webwombat/configs.py
webwombat/filters.py
webwombat/g.lark
webwombat/handler.py
webwombat/logger.py
webwombat/logs.html
webwombat/main.js
webwombat/messages.py
webwombat/transformers.py
webwombat-0.0.2.dist-info/METADATA
webwombat-0.0.2.dist-info/WHEEL
webwombat-0.0.2.dist-info/entry_points.txt
webwombat-0.0.2.dist-info/top_level.txt
webwombat-0.0.2.dist-info/RECORD
